onegov.reservation-0.7.0-py3.6-nspkg.pth
onegov/reservation/.gitignore
onegov/reservation/__init__.py
onegov/reservation/collection.py
onegov/reservation/core.py
onegov/reservation/upgrade.py
onegov/reservation/models/__init__.py
onegov/reservation/models/custom_allocation.py
onegov/reservation/models/custom_reservation.py
onegov/reservation/models/resource.py
onegov/reservation/tests/conftest.py
onegov/reservation/tests/test_collection.py
onegov/reservation/tests/test_pricing.py
onegov/reservation/tests/test_resource.py
onegov/reservation/tests/test_session.py
onegov.reservation-0.7.0.dist-info/METADATA
onegov.reservation-0.7.0.dist-info/WHEEL
onegov.reservation-0.7.0.dist-info/entry_points.txt
onegov.reservation-0.7.0.dist-info/namespace_packages.txt
onegov.reservation-0.7.0.dist-info/top_level.txt
onegov.reservation-0.7.0.dist-info/RECORD
