Metadata-Version: 2.1
Name: onegov.reservation
Version: 0.7.0
Summary: Libres integration for OneGov Cloud.
Home-page: http://github.com/OneGov/onegov.reservation
Author: Seantis GmbH
Author-email: info@seantis.ch
License: GPLv2
Platform: any
Classifier: Intended Audience :: Developers
Classifier: Programming Language :: Python :: 3 :: Only
Classifier: Programming Language :: Python :: 3.6
Classifier: Programming Language :: Python :: 3.7
Classifier: Topic :: Software Development :: Libraries :: Python Modules
Classifier: License :: OSI Approved :: GNU General Public License v2 (GPLv2)
Requires-Python: >=3.6
Requires-Dist: libres (>=0.3.1)
Requires-Dist: onegov.core (>=0.16.0)
Requires-Dist: onegov.form
Requires-Dist: onegov.pay
Provides-Extra: test
Requires-Dist: coverage ; extra == 'test'
Requires-Dist: freezegun ; extra == 'test'
Requires-Dist: onegov-testing ; extra == 'test'
Requires-Dist: pytest ; extra == 'test'
